odoo/addons/crm_multicompany_reporting_currency/README.rst
odoo/addons/crm_multicompany_reporting_currency/__init__.py
odoo/addons/crm_multicompany_reporting_currency/__manifest__.py
odoo/addons/crm_multicompany_reporting_currency/i18n/crm_multicompany_reporting_currency.pot
odoo/addons/crm_multicompany_reporting_currency/i18n/es.po
odoo/addons/crm_multicompany_reporting_currency/i18n/it.po
odoo/addons/crm_multicompany_reporting_currency/models/__init__.py
odoo/addons/crm_multicompany_reporting_currency/models/crm_lead.py
odoo/addons/crm_multicompany_reporting_currency/models/res_config_settings.py
odoo/addons/crm_multicompany_reporting_currency/readme/CONTRIBUTORS.rst
odoo/addons/crm_multicompany_reporting_currency/readme/DESCRIPTION.rst
odoo/addons/crm_multicompany_reporting_currency/static/description/icon.png
odoo/addons/crm_multicompany_reporting_currency/static/description/index.html
odoo/addons/crm_multicompany_reporting_currency/tests/__init__.py
odoo/addons/crm_multicompany_reporting_currency/tests/test_amount_multicompany_reporting_currency.py
odoo/addons/crm_multicompany_reporting_currency/views/crm_lead_views.xml
odoo_addon_crm_multicompany_reporting_currency-15.0.1.0.3.6.dist-info/METADATA
odoo_addon_crm_multicompany_reporting_currency-15.0.1.0.3.6.dist-info/WHEEL
odoo_addon_crm_multicompany_reporting_currency-15.0.1.0.3.6.dist-info/top_level.txt
odoo_addon_crm_multicompany_reporting_currency-15.0.1.0.3.6.dist-info/RECORD
